confidseal/__init__.py
confidseal/adapters/__init__.py
confidseal/adapters/partner_headers.py
confidseal/adapters/qtsp_dummy.py
confidseal/adapters/qtsp_infocert.py
confidseal/adapters/qtsp_swisscom.py
confidseal/adapters/router.py
confidseal/billing.py
confidseal/config.py
confidseal/emission_factors.yaml
confidseal/main.py
confidseal/packs/__init__.py
confidseal/packs/carbon/__init__.py
confidseal/packs/carbon/api.py
confidseal/packs/carbon/merkle.py
confidseal/packs/carbon/verify.py
confidseal/packs/compute.py
confidseal/packs/consent.py
confidseal/packs/devops.py
confidseal/packs/incident.py
confidseal/packs/model.py
confidseal/pricing.yaml
confidseal/templates/__init__.py
confidseal/templates/blank.pdf
confidseal/templates/blank_cert.py
confidseal/templates/carbon_cert.pdf
confidseal/templates/consent_note.py
confidseal/templates/devops_pdf.py
confidseal/templates/incident_receipt.py
confidseal/utils/__init__.py
confidseal/utils/emission_factors.py
confidseal/utils/merkle.py
confidseal/utils/pdf.py
confidseal/utils/stream_merkle.py
confidseal_hub-0.9.0.dist-info/METADATA
confidseal_hub-0.9.0.dist-info/WHEEL
confidseal_hub-0.9.0.dist-info/RECORD
