Metadata-Version: 2.3
Name: confidseal-hub
Version: 0.9.0
Summary: ConfidSeal – API de scellement qualifié
Author: Yannick de Murcia
Requires-Python: >=3.11,<3.13
Classifier: Programming Language :: Python :: 3
Classifier: Programming Language :: Python :: 3.11
Classifier: Programming Language :: Python :: 3.12
Requires-Dist: PyPDF2 (>=3.0.1)
Requires-Dist: PyYAML (>=6.0.1,<7.0.0)
Requires-Dist: fastapi (>=0.111.0,<0.112.0)
Requires-Dist: httpx (>=0.27.0,<0.28.0)
Requires-Dist: pydantic (>=2.7.1,<3.0.0)
Requires-Dist: pydantic-settings (>=2.2.1,<3.0.0)
Requires-Dist: typing-extensions (>=4.12.0,<5.0.0)
Requires-Dist: uvicorn[standard] (>=0.29.0,<0.30.0)
